{
    "env_id": 620,
    "lambdas": [
        {
            "lambdas": 0,
            "wcd_change": 9,
            "num_changes": 9,
            "time_taken": 4.309564113616943
        },
        {
            "lambdas": 0.0001,
            "wcd_change": 9,
            "num_changes": 9,
            "time_taken": 8.07904314994812
        },
        {
            "lambdas": 0.0002,
            "wcd_change": 9,
            "num_changes": 9,
            "time_taken": 8.646333456039429
        },
        {
            "lambdas": 0.0005,
            "wcd_change": 9,
            "num_changes": 9,
            "time_taken": 1.446889877319336
        },
        {
            "lambdas": 0.001,
            "wcd_change": 9,
            "num_changes": 9,
            "time_taken": 3.4648280143737793
        },
        {
            "lambdas": 0.002,
            "wcd_change": 9,
            "num_changes": 9,
            "time_taken": 8.398445844650269
        },
        {
            "lambdas": 0.005,
            "wcd_change": 9,
            "num_changes": 10,
            "time_taken": 11.515468835830688
        },
        {
            "lambdas": 0.01,
            "wcd_change": 8,
            "num_changes": 7,
            "time_taken": 6.29090690612793
        },
        {
            "lambdas": 0.02,
            "wcd_change": 8,
            "num_changes": 7,
            "time_taken": 5.152937650680542
        },
        {
            "lambdas": 0.05,
            "wcd_change": 8,
            "num_changes": 6,
            "time_taken": 3.509967088699341
        },
        {
            "lambdas": 0.1,
            "wcd_change": 8,
            "num_changes": 6,
            "time_taken": 2.554675340652466
        },
        {
            "lambdas": 0.2,
            "wcd_change": 8,
            "num_changes": 4,
            "time_taken": 2.1551222801208496
        },
        {
            "lambdas": 0.5,
            "wcd_change": 8,
            "num_changes": 2,
            "time_taken": 1.6413934230804443
        },
        {
            "lambdas": 1.0,
            "wcd_change": 8,
            "num_changes": 2,
            "time_taken": 1.7260684967041016
        },
        {
            "lambdas": 2,
            "wcd_change": 8,
            "num_changes": 2,
            "time_taken": 0.4822986125946045
        },
        {
            "lambdas": 5,
            "wcd_change": 0,
            "num_changes": 0,
            "time_taken": 0
        }
    ]
}