{
    "env_id": 3480,
    "lambdas": [
        {
            "lambdas": 0,
            "wcd_change": 2,
            "num_changes": 8,
            "time_taken": 0.9345493316650391
        },
        {
            "lambdas": 0.0001,
            "wcd_change": 2,
            "num_changes": 8,
            "time_taken": 0.88330078125
        },
        {
            "lambdas": 0.0002,
            "wcd_change": 2,
            "num_changes": 8,
            "time_taken": 0.805884599685669
        },
        {
            "lambdas": 0.0005,
            "wcd_change": 2,
            "num_changes": 8,
            "time_taken": 0.8109416961669922
        },
        {
            "lambdas": 0.001,
            "wcd_change": 2,
            "num_changes": 8,
            "time_taken": 1.0076379776000977
        },
        {
            "lambdas": 0.002,
            "wcd_change": 2,
            "num_changes": 8,
            "time_taken": 0.8069705963134766
        },
        {
            "lambdas": 0.005,
            "wcd_change": 2,
            "num_changes": 9,
            "time_taken": 0.9107346534729004
        },
        {
            "lambdas": 0.01,
            "wcd_change": 2,
            "num_changes": 6,
            "time_taken": 0.9157853126525879
        },
        {
            "lambdas": 0.02,
            "wcd_change": 2,
            "num_changes": 6,
            "time_taken": 1.1355249881744385
        },
        {
            "lambdas": 0.05,
            "wcd_change": -1,
            "num_changes": 5,
            "time_taken": 0.1511979103088379
        },
        {
            "lambdas": 0.1,
            "wcd_change": 2,
            "num_changes": 5,
            "time_taken": 0.1284646987915039
        },
        {
            "lambdas": 0.2,
            "wcd_change": -1,
            "num_changes": 4,
            "time_taken": 0.06252455711364746
        },
        {
            "lambdas": 0.5,
            "wcd_change": 0,
            "num_changes": 0,
            "time_taken": 0.11635136604309082
        },
        {
            "lambdas": 1.0,
            "wcd_change": 0,
            "num_changes": 0,
            "time_taken": 0
        },
        {
            "lambdas": 2,
            "wcd_change": 0,
            "num_changes": 0,
            "time_taken": 0
        },
        {
            "lambdas": 5,
            "wcd_change": 0,
            "num_changes": 0,
            "time_taken": 0
        }
    ]
}