{
    "env_id": 1607,
    "times": [
        0.3520793914794922,
        0.6839144229888916,
        0.8809547424316406,
        1.1145081520080566,
        1.3416023254394531,
        1.5284042358398438,
        1.695744276046753,
        1.695744276046753,
        1.695744276046753,
        1.695744276046753,
        1.695744276046753,
        1.695744276046753,
        1.695744276046753,
        1.695744276046753,
        1.695744276046753,
        1.695744276046753,
        1.695744276046753,
        1.695744276046753,
        1.695744276046753
    ],
    "wcd_changes": [
        1,
        1,
        1,
        1,
        -5,
        4,
        4,
        4,
        4,
        4,
        4,
        4,
        4,
        4,
        4,
        4,
        4,
        4,
        4
    ],
    "budgets": [
        [
            1,
            0
        ],
        [
            2,
            0
        ],
        [
            3,
            0
        ],
        [
            4,
            0
        ],
        [
            4,
            1
        ],
        [
            5,
            1
        ],
        [
            6,
            1
        ],
        [
            6,
            1
        ],
        [
            6,
            1
        ],
        [
            6,
            1
        ],
        [
            6,
            1
        ],
        [
            6,
            1
        ],
        [
            6,
            1
        ],
        [
            6,
            1
        ],
        [
            6,
            1
        ],
        [
            6,
            1
        ],
        [
            6,
            1
        ],
        [
            6,
            1
        ],
        [
            6,
            1
        ]
    ],
    "max_budgets": [
        19
    ],
    "num_changes": [
        [
            1,
            0
        ],
        [
            2,
            0
        ],
        [
            3,
            0
        ],
        [
            4,
            0
        ],
        [
            4,
            1
        ],
        [
            5,
            1
        ],
        [
            6,
            1
        ],
        [
            6,
            1
        ],
        [
            6,
            1
        ],
        [
            6,
            1
        ],
        [
            6,
            1
        ],
        [
            6,
            1
        ],
        [
            6,
            1
        ],
        [
            6,
            1
        ],
        [
            6,
            1
        ],
        [
            6,
            1
        ],
        [
            6,
            1
        ],
        [
            6,
            1
        ],
        [
            6,
            1
        ]
    ]
}