{
    "env_id": 2420,
    "lambdas": [
        {
            "lambdas": [
                0,
                0
            ],
            "wcd_change": 4,
            "num_changes": {
                "X": 0,
                "1": 0,
                "S": 0,
                "O": 0,
                "T": 2,
                "D": 0,
                "P": 0,
                "O+T": 2,
                "S+P+D": 0
            },
            "time_taken": 0.024274349212646484
        },
        {
            "lambdas": [
                0,
                0.001
            ],
            "wcd_change": 4,
            "num_changes": {
                "X": 0,
                "1": 0,
                "S": 0,
                "O": 0,
                "T": 2,
                "D": 0,
                "P": 0,
                "O+T": 2,
                "S+P+D": 0
            },
            "time_taken": 0.02534627914428711
        },
        {
            "lambdas": [
                0,
                0.005
            ],
            "wcd_change": 4,
            "num_changes": {
                "X": 0,
                "1": 0,
                "S": 0,
                "O": 0,
                "T": 2,
                "D": 0,
                "P": 0,
                "O+T": 2,
                "S+P+D": 0
            },
            "time_taken": 0.024713754653930664
        },
        {
            "lambdas": [
                0,
                0.01
            ],
            "wcd_change": 4,
            "num_changes": {
                "X": -1,
                "1": 0,
                "S": 0,
                "O": 0,
                "T": 0,
                "D": 0,
                "P": 5,
                "O+T": 0,
                "S+P+D": 5
            },
            "time_taken": 0.025928974151611328
        },
        {
            "lambdas": [
                0,
                0.05
            ],
            "wcd_change": 4,
            "num_changes": {
                "X": -1,
                "1": 0,
                "S": 0,
                "O": 0,
                "T": 0,
                "D": 0,
                "P": 5,
                "O+T": 0,
                "S+P+D": 5
            },
            "time_taken": 0.0334773063659668
        },
        {
            "lambdas": [
                0,
                0.1
            ],
            "wcd_change": 4,
            "num_changes": {
                "X": -1,
                "1": 0,
                "S": 0,
                "O": 0,
                "T": 0,
                "D": 0,
                "P": 5,
                "O+T": 0,
                "S+P+D": 5
            },
            "time_taken": 0.03355574607849121
        },
        {
            "lambdas": [
                0,
                0.5
            ],
            "wcd_change": 4,
            "num_changes": {
                "X": -1,
                "1": 0,
                "S": 0,
                "O": 0,
                "T": 0,
                "D": 0,
                "P": 5,
                "O+T": 0,
                "S+P+D": 5
            },
            "time_taken": 0.0334165096282959
        },
        {
            "lambdas": [
                0,
                1.0
            ],
            "wcd_change": 4,
            "num_changes": {
                "X": -1,
                "1": 0,
                "S": 0,
                "O": 0,
                "T": 0,
                "D": 0,
                "P": 5,
                "O+T": 0,
                "S+P+D": 5
            },
            "time_taken": 0.034211158752441406
        },
        {
            "lambdas": [
                0,
                5
            ],
            "wcd_change": 4,
            "num_changes": {
                "X": -1,
                "1": 0,
                "S": 0,
                "O": 0,
                "T": 0,
                "D": 0,
                "P": 5,
                "O+T": 0,
                "S+P+D": 5
            },
            "time_taken": 0.03371715545654297
        },
        {
            "lambdas": [
                0.001,
                0
            ],
            "wcd_change": 4,
            "num_changes": {
                "X": 0,
                "1": 0,
                "S": 0,
                "O": 0,
                "T": 2,
                "D": 0,
                "P": 0,
                "O+T": 2,
                "S+P+D": 0
            },
            "time_taken": 0.024425268173217773
        },
        {
            "lambdas": [
                0.001,
                0.001
            ],
            "wcd_change": 4,
            "num_changes": {
                "X": 0,
                "1": 0,
                "S": 0,
                "O": 0,
                "T": 2,
                "D": 0,
                "P": 0,
                "O+T": 2,
                "S+P+D": 0
            },
            "time_taken": 0.024527549743652344
        },
        {
            "lambdas": [
                0.001,
                0.005
            ],
            "wcd_change": 4,
            "num_changes": {
                "X": 0,
                "1": 0,
                "S": 0,
                "O": 0,
                "T": 2,
                "D": 0,
                "P": 0,
                "O+T": 2,
                "S+P+D": 0
            },
            "time_taken": 0.024580001831054688
        },
        {
            "lambdas": [
                0.001,
                0.01
            ],
            "wcd_change": 4,
            "num_changes": {
                "X": -1,
                "1": 0,
                "S": 0,
                "O": 0,
                "T": 0,
                "D": 0,
                "P": 5,
                "O+T": 0,
                "S+P+D": 5
            },
            "time_taken": 0.02635788917541504
        },
        {
            "lambdas": [
                0.001,
                0.05
            ],
            "wcd_change": 4,
            "num_changes": {
                "X": -1,
                "1": 0,
                "S": 0,
                "O": 0,
                "T": 0,
                "D": 0,
                "P": 5,
                "O+T": 0,
                "S+P+D": 5
            },
            "time_taken": 0.0333552360534668
        },
        {
            "lambdas": [
                0.001,
                0.1
            ],
            "wcd_change": 4,
            "num_changes": {
                "X": -1,
                "1": 0,
                "S": 0,
                "O": 0,
                "T": 0,
                "D": 0,
                "P": 5,
                "O+T": 0,
                "S+P+D": 5
            },
            "time_taken": 0.03314566612243652
        },
        {
            "lambdas": [
                0.001,
                0.5
            ],
            "wcd_change": 4,
            "num_changes": {
                "X": -1,
                "1": 0,
                "S": 0,
                "O": 0,
                "T": 0,
                "D": 0,
                "P": 5,
                "O+T": 0,
                "S+P+D": 5
            },
            "time_taken": 0.033536434173583984
        },
        {
            "lambdas": [
                0.001,
                1.0
            ],
            "wcd_change": 4,
            "num_changes": {
                "X": -1,
                "1": 0,
                "S": 0,
                "O": 0,
                "T": 0,
                "D": 0,
                "P": 5,
                "O+T": 0,
                "S+P+D": 5
            },
            "time_taken": 0.03401923179626465
        },
        {
            "lambdas": [
                0.001,
                5
            ],
            "wcd_change": 4,
            "num_changes": {
                "X": -1,
                "1": 0,
                "S": 0,
                "O": 0,
                "T": 0,
                "D": 0,
                "P": 5,
                "O+T": 0,
                "S+P+D": 5
            },
            "time_taken": 0.03336739540100098
        },
        {
            "lambdas": [
                0.005,
                0
            ],
            "wcd_change": 4,
            "num_changes": {
                "X": 0,
                "1": 0,
                "S": 0,
                "O": 0,
                "T": 2,
                "D": 0,
                "P": 0,
                "O+T": 2,
                "S+P+D": 0
            },
            "time_taken": 0.024152040481567383
        },
        {
            "lambdas": [
                0.005,
                0.001
            ],
            "wcd_change": 4,
            "num_changes": {
                "X": 0,
                "1": 0,
                "S": 0,
                "O": 0,
                "T": 2,
                "D": 0,
                "P": 0,
                "O+T": 2,
                "S+P+D": 0
            },
            "time_taken": 0.02400660514831543
        },
        {
            "lambdas": [
                0.005,
                0.005
            ],
            "wcd_change": 4,
            "num_changes": {
                "X": 0,
                "1": 0,
                "S": 0,
                "O": 0,
                "T": 2,
                "D": 0,
                "P": 0,
                "O+T": 2,
                "S+P+D": 0
            },
            "time_taken": 0.025458097457885742
        },
        {
            "lambdas": [
                0.005,
                0.01
            ],
            "wcd_change": 4,
            "num_changes": {
                "X": -1,
                "1": 0,
                "S": 0,
                "O": 0,
                "T": 0,
                "D": 0,
                "P": 5,
                "O+T": 0,
                "S+P+D": 5
            },
            "time_taken": 0.02632927894592285
        },
        {
            "lambdas": [
                0.005,
                0.05
            ],
            "wcd_change": 4,
            "num_changes": {
                "X": -1,
                "1": 0,
                "S": 0,
                "O": 0,
                "T": 0,
                "D": 0,
                "P": 5,
                "O+T": 0,
                "S+P+D": 5
            },
            "time_taken": 0.03430676460266113
        },
        {
            "lambdas": [
                0.005,
                0.1
            ],
            "wcd_change": 4,
            "num_changes": {
                "X": -1,
                "1": 0,
                "S": 0,
                "O": 0,
                "T": 0,
                "D": 0,
                "P": 5,
                "O+T": 0,
                "S+P+D": 5
            },
            "time_taken": 0.03408026695251465
        },
        {
            "lambdas": [
                0.005,
                0.5
            ],
            "wcd_change": 4,
            "num_changes": {
                "X": -1,
                "1": 0,
                "S": 0,
                "O": 0,
                "T": 0,
                "D": 0,
                "P": 5,
                "O+T": 0,
                "S+P+D": 5
            },
            "time_taken": 0.034261465072631836
        },
        {
            "lambdas": [
                0.005,
                1.0
            ],
            "wcd_change": 4,
            "num_changes": {
                "X": -1,
                "1": 0,
                "S": 0,
                "O": 0,
                "T": 0,
                "D": 0,
                "P": 5,
                "O+T": 0,
                "S+P+D": 5
            },
            "time_taken": 0.033823490142822266
        },
        {
            "lambdas": [
                0.005,
                5
            ],
            "wcd_change": 4,
            "num_changes": {
                "X": -1,
                "1": 0,
                "S": 0,
                "O": 0,
                "T": 0,
                "D": 0,
                "P": 5,
                "O+T": 0,
                "S+P+D": 5
            },
            "time_taken": 0.03334355354309082
        },
        {
            "lambdas": [
                0.01,
                0
            ],
            "wcd_change": 4,
            "num_changes": {
                "X": 0,
                "1": 0,
                "S": 0,
                "O": 0,
                "T": 2,
                "D": 0,
                "P": 0,
                "O+T": 2,
                "S+P+D": 0
            },
            "time_taken": 0.025763988494873047
        },
        {
            "lambdas": [
                0.01,
                0.001
            ],
            "wcd_change": 4,
            "num_changes": {
                "X": 0,
                "1": 0,
                "S": 0,
                "O": 0,
                "T": 2,
                "D": 0,
                "P": 0,
                "O+T": 2,
                "S+P+D": 0
            },
            "time_taken": 0.02577495574951172
        },
        {
            "lambdas": [
                0.01,
                0.005
            ],
            "wcd_change": 4,
            "num_changes": {
                "X": 0,
                "1": 0,
                "S": 0,
                "O": 0,
                "T": 2,
                "D": 0,
                "P": 0,
                "O+T": 2,
                "S+P+D": 0
            },
            "time_taken": 0.02442765235900879
        },
        {
            "lambdas": [
                0.01,
                0.01
            ],
            "wcd_change": 4,
            "num_changes": {
                "X": 0,
                "1": 0,
                "S": 0,
                "O": 0,
                "T": 2,
                "D": 0,
                "P": 0,
                "O+T": 2,
                "S+P+D": 0
            },
            "time_taken": 0.024182796478271484
        },
        {
            "lambdas": [
                0.01,
                0.05
            ],
            "wcd_change": 4,
            "num_changes": {
                "X": -1,
                "1": 0,
                "S": 0,
                "O": 0,
                "T": 0,
                "D": 0,
                "P": 5,
                "O+T": 0,
                "S+P+D": 5
            },
            "time_taken": 0.034124135971069336
        },
        {
            "lambdas": [
                0.01,
                0.1
            ],
            "wcd_change": 4,
            "num_changes": {
                "X": -1,
                "1": 0,
                "S": 0,
                "O": 0,
                "T": 0,
                "D": 0,
                "P": 5,
                "O+T": 0,
                "S+P+D": 5
            },
            "time_taken": 0.03458046913146973
        },
        {
            "lambdas": [
                0.01,
                0.5
            ],
            "wcd_change": 4,
            "num_changes": {
                "X": -1,
                "1": 0,
                "S": 0,
                "O": 0,
                "T": 0,
                "D": 0,
                "P": 5,
                "O+T": 0,
                "S+P+D": 5
            },
            "time_taken": 0.03380608558654785
        },
        {
            "lambdas": [
                0.01,
                1.0
            ],
            "wcd_change": 4,
            "num_changes": {
                "X": -1,
                "1": 0,
                "S": 0,
                "O": 0,
                "T": 0,
                "D": 0,
                "P": 5,
                "O+T": 0,
                "S+P+D": 5
            },
            "time_taken": 0.03420877456665039
        },
        {
            "lambdas": [
                0.01,
                5
            ],
            "wcd_change": 4,
            "num_changes": {
                "X": -1,
                "1": 0,
                "S": 0,
                "O": 0,
                "T": 0,
                "D": 0,
                "P": 5,
                "O+T": 0,
                "S+P+D": 5
            },
            "time_taken": 0.03407549858093262
        },
        {
            "lambdas": [
                0.05,
                0
            ],
            "wcd_change": 0,
            "num_changes": {
                "X": -1,
                "1": 0,
                "S": 0,
                "O": 2,
                "T": 0,
                "D": 0,
                "P": 0,
                "O+T": 2,
                "S+P+D": 0
            },
            "time_taken": 0.03400158882141113
        },
        {
            "lambdas": [
                0.05,
                0.001
            ],
            "wcd_change": 0,
            "num_changes": {
                "X": -1,
                "1": 0,
                "S": 0,
                "O": 2,
                "T": 0,
                "D": 0,
                "P": 0,
                "O+T": 2,
                "S+P+D": 0
            },
            "time_taken": 0.03390669822692871
        },
        {
            "lambdas": [
                0.05,
                0.005
            ],
            "wcd_change": 0,
            "num_changes": {
                "X": -1,
                "1": 0,
                "S": 0,
                "O": 2,
                "T": 0,
                "D": 0,
                "P": 0,
                "O+T": 2,
                "S+P+D": 0
            },
            "time_taken": 0.03449869155883789
        },
        {
            "lambdas": [
                0.05,
                0.01
            ],
            "wcd_change": 0,
            "num_changes": {
                "X": -1,
                "1": 0,
                "S": 0,
                "O": 2,
                "T": 0,
                "D": 0,
                "P": 0,
                "O+T": 2,
                "S+P+D": 0
            },
            "time_taken": 0.03438878059387207
        },
        {
            "lambdas": [
                0.05,
                0.05
            ],
            "wcd_change": 4,
            "num_changes": {
                "X": -1,
                "1": 0,
                "S": 0,
                "O": 0,
                "T": 0,
                "D": 0,
                "P": 5,
                "O+T": 0,
                "S+P+D": 5
            },
            "time_taken": 0.03365063667297363
        },
        {
            "lambdas": [
                0.05,
                0.1
            ],
            "wcd_change": 4,
            "num_changes": {
                "X": -1,
                "1": 0,
                "S": 0,
                "O": 0,
                "T": 0,
                "D": 0,
                "P": 5,
                "O+T": 0,
                "S+P+D": 5
            },
            "time_taken": 0.03366351127624512
        },
        {
            "lambdas": [
                0.05,
                0.5
            ],
            "wcd_change": 4,
            "num_changes": {
                "X": -1,
                "1": 0,
                "S": 0,
                "O": 0,
                "T": 0,
                "D": 0,
                "P": 5,
                "O+T": 0,
                "S+P+D": 5
            },
            "time_taken": 0.034020423889160156
        },
        {
            "lambdas": [
                0.05,
                1.0
            ],
            "wcd_change": 4,
            "num_changes": {
                "X": -1,
                "1": 0,
                "S": 0,
                "O": 0,
                "T": 0,
                "D": 0,
                "P": 5,
                "O+T": 0,
                "S+P+D": 5
            },
            "time_taken": 0.033740997314453125
        },
        {
            "lambdas": [
                0.05,
                5
            ],
            "wcd_change": 4,
            "num_changes": {
                "X": -1,
                "1": 0,
                "S": 0,
                "O": 0,
                "T": 0,
                "D": 0,
                "P": 5,
                "O+T": 0,
                "S+P+D": 5
            },
            "time_taken": 0.03377556800842285
        },
        {
            "lambdas": [
                0.1,
                0
            ],
            "wcd_change": 0,
            "num_changes": {
                "X": -1,
                "1": 0,
                "S": 0,
                "O": 2,
                "T": 0,
                "D": 0,
                "P": 0,
                "O+T": 2,
                "S+P+D": 0
            },
            "time_taken": 0.034210205078125
        },
        {
            "lambdas": [
                0.1,
                0.001
            ],
            "wcd_change": 0,
            "num_changes": {
                "X": -1,
                "1": 0,
                "S": 0,
                "O": 2,
                "T": 0,
                "D": 0,
                "P": 0,
                "O+T": 2,
                "S+P+D": 0
            },
            "time_taken": 0.03374290466308594
        },
        {
            "lambdas": [
                0.1,
                0.005
            ],
            "wcd_change": 0,
            "num_changes": {
                "X": -1,
                "1": 0,
                "S": 0,
                "O": 2,
                "T": 0,
                "D": 0,
                "P": 0,
                "O+T": 2,
                "S+P+D": 0
            },
            "time_taken": 0.03395366668701172
        },
        {
            "lambdas": [
                0.1,
                0.01
            ],
            "wcd_change": 0,
            "num_changes": {
                "X": -1,
                "1": 0,
                "S": 0,
                "O": 2,
                "T": 0,
                "D": 0,
                "P": 0,
                "O+T": 2,
                "S+P+D": 0
            },
            "time_taken": 0.03388476371765137
        },
        {
            "lambdas": [
                0.1,
                0.05
            ],
            "wcd_change": 0,
            "num_changes": {
                "X": -1,
                "1": 0,
                "S": 0,
                "O": 2,
                "T": 0,
                "D": 0,
                "P": 0,
                "O+T": 2,
                "S+P+D": 0
            },
            "time_taken": 0.03524446487426758
        },
        {
            "lambdas": [
                0.1,
                0.1
            ],
            "wcd_change": 4,
            "num_changes": {
                "X": -1,
                "1": 0,
                "S": 0,
                "O": 0,
                "T": 0,
                "D": 0,
                "P": 5,
                "O+T": 0,
                "S+P+D": 5
            },
            "time_taken": 0.03433847427368164
        },
        {
            "lambdas": [
                0.1,
                0.5
            ],
            "wcd_change": 4,
            "num_changes": {
                "X": -1,
                "1": 0,
                "S": 0,
                "O": 0,
                "T": 0,
                "D": 0,
                "P": 5,
                "O+T": 0,
                "S+P+D": 5
            },
            "time_taken": 0.03481793403625488
        },
        {
            "lambdas": [
                0.1,
                1.0
            ],
            "wcd_change": 4,
            "num_changes": {
                "X": -1,
                "1": 0,
                "S": 0,
                "O": 0,
                "T": 0,
                "D": 0,
                "P": 5,
                "O+T": 0,
                "S+P+D": 5
            },
            "time_taken": 0.03361964225769043
        },
        {
            "lambdas": [
                0.1,
                5
            ],
            "wcd_change": 4,
            "num_changes": {
                "X": -1,
                "1": 0,
                "S": 0,
                "O": 0,
                "T": 0,
                "D": 0,
                "P": 5,
                "O+T": 0,
                "S+P+D": 5
            },
            "time_taken": 0.033591508865356445
        },
        {
            "lambdas": [
                0.5,
                0
            ],
            "wcd_change": 0,
            "num_changes": {
                "X": -1,
                "1": 0,
                "S": 0,
                "O": 2,
                "T": 0,
                "D": 0,
                "P": 0,
                "O+T": 2,
                "S+P+D": 0
            },
            "time_taken": 0.0354616641998291
        },
        {
            "lambdas": [
                0.5,
                0.001
            ],
            "wcd_change": 0,
            "num_changes": {
                "X": -1,
                "1": 0,
                "S": 0,
                "O": 2,
                "T": 0,
                "D": 0,
                "P": 0,
                "O+T": 2,
                "S+P+D": 0
            },
            "time_taken": 0.034705162048339844
        },
        {
            "lambdas": [
                0.5,
                0.005
            ],
            "wcd_change": 0,
            "num_changes": {
                "X": -1,
                "1": 0,
                "S": 0,
                "O": 2,
                "T": 0,
                "D": 0,
                "P": 0,
                "O+T": 2,
                "S+P+D": 0
            },
            "time_taken": 0.0346224308013916
        },
        {
            "lambdas": [
                0.5,
                0.01
            ],
            "wcd_change": 0,
            "num_changes": {
                "X": -1,
                "1": 0,
                "S": 0,
                "O": 2,
                "T": 0,
                "D": 0,
                "P": 0,
                "O+T": 2,
                "S+P+D": 0
            },
            "time_taken": 0.03387904167175293
        },
        {
            "lambdas": [
                0.5,
                0.05
            ],
            "wcd_change": 0,
            "num_changes": {
                "X": -1,
                "1": 0,
                "S": 0,
                "O": 2,
                "T": 0,
                "D": 0,
                "P": 0,
                "O+T": 2,
                "S+P+D": 0
            },
            "time_taken": 0.034173011779785156
        },
        {
            "lambdas": [
                0.5,
                0.1
            ],
            "wcd_change": 0,
            "num_changes": {
                "X": -1,
                "1": 0,
                "S": 0,
                "O": 2,
                "T": 0,
                "D": 0,
                "P": 0,
                "O+T": 2,
                "S+P+D": 0
            },
            "time_taken": 0.03535342216491699
        },
        {
            "lambdas": [
                0.5,
                0.5
            ],
            "wcd_change": 4,
            "num_changes": {
                "X": -1,
                "1": 0,
                "S": 0,
                "O": 0,
                "T": 0,
                "D": 0,
                "P": 5,
                "O+T": 0,
                "S+P+D": 5
            },
            "time_taken": 0.03411436080932617
        },
        {
            "lambdas": [
                0.5,
                1.0
            ],
            "wcd_change": 4,
            "num_changes": {
                "X": -1,
                "1": 0,
                "S": 0,
                "O": 0,
                "T": 0,
                "D": 0,
                "P": 5,
                "O+T": 0,
                "S+P+D": 5
            },
            "time_taken": 0.034487009048461914
        },
        {
            "lambdas": [
                0.5,
                5
            ],
            "wcd_change": 4,
            "num_changes": {
                "X": -1,
                "1": 0,
                "S": 0,
                "O": 0,
                "T": 0,
                "D": 0,
                "P": 5,
                "O+T": 0,
                "S+P+D": 5
            },
            "time_taken": 0.03336524963378906
        },
        {
            "lambdas": [
                1.0,
                0
            ],
            "wcd_change": 0,
            "num_changes": {
                "X": -1,
                "1": 0,
                "S": 0,
                "O": 2,
                "T": 0,
                "D": 0,
                "P": 0,
                "O+T": 2,
                "S+P+D": 0
            },
            "time_taken": 0.03383994102478027
        },
        {
            "lambdas": [
                1.0,
                0.001
            ],
            "wcd_change": 0,
            "num_changes": {
                "X": -1,
                "1": 0,
                "S": 0,
                "O": 2,
                "T": 0,
                "D": 0,
                "P": 0,
                "O+T": 2,
                "S+P+D": 0
            },
            "time_taken": 0.03411126136779785
        },
        {
            "lambdas": [
                1.0,
                0.005
            ],
            "wcd_change": 0,
            "num_changes": {
                "X": -1,
                "1": 0,
                "S": 0,
                "O": 2,
                "T": 0,
                "D": 0,
                "P": 0,
                "O+T": 2,
                "S+P+D": 0
            },
            "time_taken": 0.03388547897338867
        },
        {
            "lambdas": [
                1.0,
                0.01
            ],
            "wcd_change": 0,
            "num_changes": {
                "X": -1,
                "1": 0,
                "S": 0,
                "O": 2,
                "T": 0,
                "D": 0,
                "P": 0,
                "O+T": 2,
                "S+P+D": 0
            },
            "time_taken": 0.033608198165893555
        },
        {
            "lambdas": [
                1.0,
                0.05
            ],
            "wcd_change": 0,
            "num_changes": {
                "X": -1,
                "1": 0,
                "S": 0,
                "O": 2,
                "T": 0,
                "D": 0,
                "P": 0,
                "O+T": 2,
                "S+P+D": 0
            },
            "time_taken": 0.03451704978942871
        },
        {
            "lambdas": [
                1.0,
                0.1
            ],
            "wcd_change": 0,
            "num_changes": {
                "X": -1,
                "1": 0,
                "S": 0,
                "O": 2,
                "T": 0,
                "D": 0,
                "P": 0,
                "O+T": 2,
                "S+P+D": 0
            },
            "time_taken": 0.033905029296875
        },
        {
            "lambdas": [
                1.0,
                0.5
            ],
            "wcd_change": 0,
            "num_changes": {
                "X": -1,
                "1": 0,
                "S": 0,
                "O": 2,
                "T": 0,
                "D": 0,
                "P": 0,
                "O+T": 2,
                "S+P+D": 0
            },
            "time_taken": 0.035010576248168945
        },
        {
            "lambdas": [
                1.0,
                1.0
            ],
            "wcd_change": 4,
            "num_changes": {
                "X": -1,
                "1": 0,
                "S": 0,
                "O": 0,
                "T": 0,
                "D": 0,
                "P": 5,
                "O+T": 0,
                "S+P+D": 5
            },
            "time_taken": 0.03363394737243652
        },
        {
            "lambdas": [
                1.0,
                5
            ],
            "wcd_change": 4,
            "num_changes": {
                "X": -1,
                "1": 0,
                "S": 0,
                "O": 0,
                "T": 0,
                "D": 0,
                "P": 5,
                "O+T": 0,
                "S+P+D": 5
            },
            "time_taken": 0.03525900840759277
        },
        {
            "lambdas": [
                5,
                0
            ],
            "wcd_change": 0,
            "num_changes": {
                "X": -1,
                "1": 0,
                "S": 0,
                "O": 2,
                "T": 0,
                "D": 0,
                "P": 0,
                "O+T": 2,
                "S+P+D": 0
            },
            "time_taken": 0.034142255783081055
        },
        {
            "lambdas": [
                5,
                0.001
            ],
            "wcd_change": 0,
            "num_changes": {
                "X": -1,
                "1": 0,
                "S": 0,
                "O": 2,
                "T": 0,
                "D": 0,
                "P": 0,
                "O+T": 2,
                "S+P+D": 0
            },
            "time_taken": 0.03348684310913086
        },
        {
            "lambdas": [
                5,
                0.005
            ],
            "wcd_change": 0,
            "num_changes": {
                "X": -1,
                "1": 0,
                "S": 0,
                "O": 2,
                "T": 0,
                "D": 0,
                "P": 0,
                "O+T": 2,
                "S+P+D": 0
            },
            "time_taken": 0.034055233001708984
        },
        {
            "lambdas": [
                5,
                0.01
            ],
            "wcd_change": 0,
            "num_changes": {
                "X": -1,
                "1": 0,
                "S": 0,
                "O": 2,
                "T": 0,
                "D": 0,
                "P": 0,
                "O+T": 2,
                "S+P+D": 0
            },
            "time_taken": 0.03562760353088379
        },
        {
            "lambdas": [
                5,
                0.05
            ],
            "wcd_change": 0,
            "num_changes": {
                "X": -1,
                "1": 0,
                "S": 0,
                "O": 2,
                "T": 0,
                "D": 0,
                "P": 0,
                "O+T": 2,
                "S+P+D": 0
            },
            "time_taken": 0.03406953811645508
        },
        {
            "lambdas": [
                5,
                0.1
            ],
            "wcd_change": 0,
            "num_changes": {
                "X": -1,
                "1": 0,
                "S": 0,
                "O": 2,
                "T": 0,
                "D": 0,
                "P": 0,
                "O+T": 2,
                "S+P+D": 0
            },
            "time_taken": 0.033676862716674805
        },
        {
            "lambdas": [
                5,
                0.5
            ],
            "wcd_change": 0,
            "num_changes": {
                "X": -1,
                "1": 0,
                "S": 0,
                "O": 2,
                "T": 0,
                "D": 0,
                "P": 0,
                "O+T": 2,
                "S+P+D": 0
            },
            "time_taken": 0.033588409423828125
        },
        {
            "lambdas": [
                5,
                1.0
            ],
            "wcd_change": 0,
            "num_changes": {
                "X": -1,
                "1": 0,
                "S": 0,
                "O": 2,
                "T": 0,
                "D": 0,
                "P": 0,
                "O+T": 2,
                "S+P+D": 0
            },
            "time_taken": 0.03362917900085449
        },
        {
            "lambdas": [
                5,
                5
            ],
            "wcd_change": 4,
            "num_changes": {
                "X": -1,
                "1": 0,
                "S": 0,
                "O": 0,
                "T": 0,
                "D": 0,
                "P": 5,
                "O+T": 0,
                "S+P+D": 5
            },
            "time_taken": 0.03380441665649414
        }
    ]
}